{
  "experiment_name": "Cell locomotion with driver molecule.",
  "experiment_reps": 1,
  "experiment_guid": "7f6f3874-bd40-41d4-bf9d-9bef0ea32235",
  "experiment_description": "Cell moves in the direction of the CXCL13 linear gradient (right to left) maintained by Dirichlet BCs. Cytosol molecule A* drives locomotion.",
  "scenario": {
    "$type": "Daphne.TissueScenario, Daphne",
    "cellpopulations": [
      {
        "Cell": {
          "CurrentDeathState": 0,
          "CurrentDivState": 0,
          "renderLabel": "094518dc-b53c-4887-b4e3-7c5ca066e67d",
          "CellName": "Leukocyte_staticReceptor_motile",
          "CellRadius": 5.0,
          "locomotor_mol_guid_ref": "c7b04294-a127-4801-a4e7-4cfbf86fcfed",
          "TransductionConstant": {
            "ParamDistr": null,
            "ConstValue": 100.0,
            "DistributionType": 0
          },
          "DragCoefficient": {
            "ParamDistr": null,
            "ConstValue": 1.0,
            "DistributionType": 0
          },
          "Sigma": {
            "ParamDistr": null,
            "ConstValue": 0.0,
            "DistributionType": 0
          },
          "membrane": {
            "molpops": [
              {
                "molpop_guid": "6caf53b8-de14-4d55-a2b9-1fa6d218d37c",
                "molecule": {
                  "Name": "CXCR5|",
                  "renderLabel": "8dbfbfca-2b31-4ba0-a67d-1cb1b2bed436",
                  "MolecularWeight": 43.0,
                  "EffectiveRadius": 1.0,
                  "DiffusionCoefficient": 1E-07,
                  "molecule_location": 1,
                  "entity_guid": "8dbfbfca-2b31-4ba0-a67d-1cb1b2bed436"
                },
                "Name": "CXCR5|",
                "report_mp": {
                  "mp_extended": 0,
                  "molpop_guid_ref": "6caf53b8-de14-4d55-a2b9-1fa6d218d37c"
                },
                "mp_distribution": {
                  "$type": "Daphne.MolPopHomogeneousLevel, Daphne",
                  "concentration": 44.0,
                  "mp_distribution_type": 0,
                  "boundaryCondition": null
                },
                "renderLabel": "8dbfbfca-2b31-4ba0-a67d-1cb1b2bed436"
              },
              {
                "molpop_guid": "0c7780b0-96c5-4f87-ab75-f6c6d3a20191",
                "molecule": {
                  "Name": "CXCL13:CXCR5|",
                  "renderLabel": "b8126221-1e3c-49da-b2bd-6d30f47b0b1f",
                  "MolecularWeight": 50.96,
                  "EffectiveRadius": 1.0,
                  "DiffusionCoefficient": 1E-07,
                  "molecule_location": 1,
                  "entity_guid": "b8126221-1e3c-49da-b2bd-6d30f47b0b1f"
                },
                "Name": "CXCL13:CXCR5|",
                "report_mp": {
                  "mp_extended": 0,
                  "molpop_guid_ref": "0c7780b0-96c5-4f87-ab75-f6c6d3a20191"
                },
                "mp_distribution": {
                  "$type": "Daphne.MolPopHomogeneousLevel, Daphne",
                  "concentration": 0.0,
                  "mp_distribution_type": 0,
                  "boundaryCondition": null
                },
                "renderLabel": "b8126221-1e3c-49da-b2bd-6d30f47b0b1f"
              }
            ],
            "Reactions": [],
            "reaction_complexes": []
          },
          "cytosol": {
            "molpops": [
              {
                "molpop_guid": "0dde43d3-33b7-4444-8022-cd4fa9ab55af",
                "molecule": {
                  "Name": "A",
                  "renderLabel": "6afbee57-6dcc-4bd6-bc14-1e10116e8388",
                  "MolecularWeight": 1.0,
                  "EffectiveRadius": 1.0,
                  "DiffusionCoefficient": 750.0,
                  "molecule_location": 0,
                  "entity_guid": "6afbee57-6dcc-4bd6-bc14-1e10116e8388"
                },
                "Name": "A",
                "report_mp": {
                  "mp_extended": 0,
                  "molpop_guid_ref": "0dde43d3-33b7-4444-8022-cd4fa9ab55af"
                },
                "mp_distribution": {
                  "$type": "Daphne.MolPopHomogeneousLevel, Daphne",
                  "concentration": 250.0,
                  "mp_distribution_type": 0,
                  "boundaryCondition": null
                },
                "renderLabel": "6afbee57-6dcc-4bd6-bc14-1e10116e8388"
              },
              {
                "molpop_guid": "cf2fa1fc-41cc-4919-b24b-08eb63283b46",
                "molecule": {
                  "Name": "A*",
                  "renderLabel": "c7b04294-a127-4801-a4e7-4cfbf86fcfed",
                  "MolecularWeight": 1.0,
                  "EffectiveRadius": 1.0,
                  "DiffusionCoefficient": 7.5,
                  "molecule_location": 0,
                  "entity_guid": "c7b04294-a127-4801-a4e7-4cfbf86fcfed"
                },
                "Name": "A*",
                "report_mp": {
                  "mp_extended": 0,
                  "molpop_guid_ref": "cf2fa1fc-41cc-4919-b24b-08eb63283b46"
                },
                "mp_distribution": {
                  "$type": "Daphne.MolPopHomogeneousLevel, Daphne",
                  "concentration": 0.0,
                  "mp_distribution_type": 0,
                  "boundaryCondition": null
                },
                "renderLabel": "c7b04294-a127-4801-a4e7-4cfbf86fcfed"
              },
              {
                "molpop_guid": "f7953823-49b3-420f-a43b-c42de20639b6",
                "molecule": {
                  "Name": "sApop",
                  "renderLabel": "e411f784-cf2a-40b9-9674-61ea12746bd5",
                  "MolecularWeight": 1.0,
                  "EffectiveRadius": 1.0,
                  "DiffusionCoefficient": 1.0,
                  "molecule_location": 0,
                  "entity_guid": "e411f784-cf2a-40b9-9674-61ea12746bd5"
                },
                "Name": "sApop",
                "report_mp": {
                  "mp_extended": 0,
                  "molpop_guid_ref": "f7953823-49b3-420f-a43b-c42de20639b6"
                },
                "mp_distribution": {
                  "$type": "Daphne.MolPopHomogeneousLevel, Daphne",
                  "concentration": 0.0,
                  "mp_distribution_type": 0,
                  "boundaryCondition": null
                },
                "renderLabel": "e411f784-cf2a-40b9-9674-61ea12746bd5"
              }
            ],
            "Reactions": [
              {
                "reactants_molecule_guid_ref": [
                  "6afbee57-6dcc-4bd6-bc14-1e10116e8388"
                ],
                "products_molecule_guid_ref": [
                  "c7b04294-a127-4801-a4e7-4cfbf86fcfed"
                ],
                "modifiers_molecule_guid_ref": [
                  "b8126221-1e3c-49da-b2bd-6d30f47b0b1f"
                ],
                "reaction_template_guid_ref": "ee8712d9-26be-4a8a-b137-7da1a455eb3e",
                "rate_const": 0.005,
                "TotalReactionString": "A + CXCL13:CXCR5| -> A* + CXCL13:CXCR5|",
                "entity_guid": "7c613bb0-77f6-4e2d-afb0-b0139ddb2601"
              },
              {
                "reactants_molecule_guid_ref": [
                  "c7b04294-a127-4801-a4e7-4cfbf86fcfed"
                ],
                "products_molecule_guid_ref": [
                  "6afbee57-6dcc-4bd6-bc14-1e10116e8388"
                ],
                "modifiers_molecule_guid_ref": [],
                "reaction_template_guid_ref": "5725c441-7119-4967-a274-9d70d6b72283",
                "rate_const": 0.0005,
                "TotalReactionString": "A* -> A",
                "entity_guid": "19f358cf-0984-4653-a3e1-a296cd186863"
              },
              {
                "reactants_molecule_guid_ref": [],
                "products_molecule_guid_ref": [
                  "e411f784-cf2a-40b9-9674-61ea12746bd5"
                ],
                "modifiers_molecule_guid_ref": [
                  "9577901c-7701-47fa-8ffe-5bb1a95cfd0c"
                ],
                "reaction_template_guid_ref": "91a501cf-b1ff-42f2-a3b9-0f179f805ce0",
                "rate_const": 1.6666666666666667,
                "TotalReactionString": "gApop -> sApop + gApop",
                "entity_guid": "e50ff360-0592-488c-b941-69797e30dbe6"
              }
            ],
            "reaction_complexes": []
          },
          "genes": [
            {
              "Name": "gApop",
              "CopyNumber": 2,
              "ActivationLevel": 1.0,
              "entity_guid": "9577901c-7701-47fa-8ffe-5bb1a95cfd0c"
            }
          ],
          "diff_scheme": null,
          "death_driver": null,
          "div_scheme": null,
          "entity_guid": "094518dc-b53c-4887-b4e3-7c5ca066e67d"
        },
        "cellpopulation_name": "Leukocyte_staticReceptor_motile",
        "cellpopulation_guid": "2b39fa14-2622-41cf-9c4a-cb45b59db089",
        "cellpopulation_id": 0,
        "report_xvf": {
          "position": true,
          "velocity": true,
          "force": true
        },
        "reportStates": {
          "Death": false,
          "Division": false,
          "Differentiation": false
        },
        "ecm_probe": [
          {
            "mean": false,
            "mp_extended": 2,
            "molpop_guid_ref": "ec71fb75-e2e6-4a92-aebf-d34ef499dacc"
          }
        ],
        "number": 1,
        "CellStates": [
          {
            "spState": {
              "X": [
                185.0,
                95.0,
                95.0
              ],
              "V": [
                0.0,
                0.0,
                0.0
              ],
              "F": [
                0.0,
                0.0,
                0.0
              ]
            },
            "cmState": {
              "molPopDict": {}
            },
            "cbState": {
              "deathDriveState": -1,
              "divisionDriverState": -1,
              "differentiationDriverState": -1
            },
            "cgState": {
              "geneDict": {}
            },
            "CellGeneration": 0
          }
        ],
        "cellPopDist": {
          "$type": "Daphne.CellPopSpecific, Daphne",
          "DistType": 0,
          "Extents": [
            200.0,
            200.0,
            200.0
          ],
          "MinDisSquared": 100.0
        },
        "renderLabel": "094518dc-b53c-4887-b4e3-7c5ca066e67d"
      }
    ],
    "RenderSkinName": "default",
    "popOptions": {
      "cellPopOptions": [
        {
          "renderOn": true,
          "renderMethod": 0,
          "name": "Leukocyte_staticReceptor_motile",
          "renderLabel": "094518dc-b53c-4887-b4e3-7c5ca066e67d"
        }
      ],
      "molPopOptions": [
        {
          "renderOn": false,
          "renderMethod": 10,
          "name": "CXCL13",
          "renderLabel": "8312e805-3bb5-4c0b-afd4-ab5c2333591d"
        }
      ]
    },
    "time_config": {
      "duration": 30.0,
      "rendering_interval": 0.3,
      "sampling_interval": 0.3,
      "integrator_step": 0.001
    },
    "simInterpolate": 1,
    "simCellSize": 3,
    "environment": {
      "$type": "Daphne.ConfigECSEnvironment, Daphne",
      "extent_x": 200,
      "extent_y": 200,
      "extent_z": 200,
      "gridstep": 10.0,
      "NumGridPts": [
        21,
        21,
        21
      ],
      "toroidal": false,
      "comp": {
        "molpops": [
          {
            "molpop_guid": "ec71fb75-e2e6-4a92-aebf-d34ef499dacc",
            "molecule": {
              "Name": "CXCL13",
              "renderLabel": "8312e805-3bb5-4c0b-afd4-ab5c2333591d",
              "MolecularWeight": 7.96,
              "EffectiveRadius": 1.0,
              "DiffusionCoefficient": 4500.0,
              "molecule_location": 0,
              "entity_guid": "8312e805-3bb5-4c0b-afd4-ab5c2333591d"
            },
            "Name": "CXCL13",
            "report_mp": {
              "$type": "Daphne.ReportECM, Daphne",
              "mean": false,
              "mp_extended": 0,
              "molpop_guid_ref": "ec71fb75-e2e6-4a92-aebf-d34ef499dacc"
            },
            "mp_distribution": {
              "$type": "Daphne.MolPopLinear, Daphne",
              "x1": 0.0,
              "dim": 0,
              "boundary_face": 1,
              "mp_distribution_type": 1,
              "boundaryCondition": [
                {
                  "boundaryType": 1,
                  "boundary": 1,
                  "concVal": 0.1520555
                },
                {
                  "boundaryType": 1,
                  "boundary": 2,
                  "concVal": 0.0
                }
              ]
            },
            "renderLabel": "8312e805-3bb5-4c0b-afd4-ab5c2333591d"
          }
        ],
        "Reactions": [
          {
            "reactants_molecule_guid_ref": [
              "8312e805-3bb5-4c0b-afd4-ab5c2333591d",
              "8dbfbfca-2b31-4ba0-a67d-1cb1b2bed436"
            ],
            "products_molecule_guid_ref": [
              "b8126221-1e3c-49da-b2bd-6d30f47b0b1f"
            ],
            "modifiers_molecule_guid_ref": [],
            "reaction_template_guid_ref": "6175f910-6b3e-4cbe-85c6-ac6842e80dd5",
            "rate_const": 16.25,
            "TotalReactionString": "CXCL13 + CXCR5| -> CXCL13:CXCR5|",
            "entity_guid": "addf048e-319a-4780-a631-f9221eee526f"
          },
          {
            "reactants_molecule_guid_ref": [
              "b8126221-1e3c-49da-b2bd-6d30f47b0b1f"
            ],
            "products_molecule_guid_ref": [
              "8312e805-3bb5-4c0b-afd4-ab5c2333591d",
              "8dbfbfca-2b31-4ba0-a67d-1cb1b2bed436"
            ],
            "modifiers_molecule_guid_ref": [],
            "reaction_template_guid_ref": "0af1638c-bc13-4c3a-9eb1-13772b3c907e",
            "rate_const": 0.494,
            "TotalReactionString": "CXCL13:CXCR5| -> CXCL13 + CXCR5|",
            "entity_guid": "b2b31aad-11ac-41ac-b321-7eb664808900"
          }
        ],
        "reaction_complexes": []
      }
    }
  },
  "sim_params": {
    "phi1": 100.0,
    "phi2": 0.0,
    "deathConstant": 0.001,
    "deathOrder": 1,
    "globalRandomSeed": -435430449
  },
  "reporter_file_name": "Loco_test",
  "entity_repository": {
    "reaction_complexes": [],
    "cells": [
      {
        "CurrentDeathState": 0,
        "CurrentDivState": 0,
        "renderLabel": "094518dc-b53c-4887-b4e3-7c5ca066e67d",
        "CellName": "Leukocyte_staticReceptor_motile",
        "CellRadius": 5.0,
        "locomotor_mol_guid_ref": "c7b04294-a127-4801-a4e7-4cfbf86fcfed",
        "TransductionConstant": {
          "ParamDistr": null,
          "ConstValue": 100.0,
          "DistributionType": 0
        },
        "DragCoefficient": {
          "ParamDistr": null,
          "ConstValue": 1.0,
          "DistributionType": 0
        },
        "Sigma": {
          "ParamDistr": null,
          "ConstValue": 0.0,
          "DistributionType": 0
        },
        "membrane": {
          "molpops": [
            {
              "molpop_guid": "6caf53b8-de14-4d55-a2b9-1fa6d218d37c",
              "molecule": {
                "Name": "CXCR5|",
                "renderLabel": "8dbfbfca-2b31-4ba0-a67d-1cb1b2bed436",
                "MolecularWeight": 43.0,
                "EffectiveRadius": 1.0,
                "DiffusionCoefficient": 1E-07,
                "molecule_location": 1,
                "entity_guid": "8dbfbfca-2b31-4ba0-a67d-1cb1b2bed436"
              },
              "Name": "CXCR5|",
              "report_mp": {
                "mp_extended": 2,
                "molpop_guid_ref": "6caf53b8-de14-4d55-a2b9-1fa6d218d37c"
              },
              "mp_distribution": {
                "$type": "Daphne.MolPopHomogeneousLevel, Daphne",
                "concentration": 44.0,
                "mp_distribution_type": 0,
                "boundaryCondition": null
              },
              "renderLabel": "8dbfbfca-2b31-4ba0-a67d-1cb1b2bed436"
            },
            {
              "molpop_guid": "0c7780b0-96c5-4f87-ab75-f6c6d3a20191",
              "molecule": {
                "Name": "CXCL13:CXCR5|",
                "renderLabel": "b8126221-1e3c-49da-b2bd-6d30f47b0b1f",
                "MolecularWeight": 50.96,
                "EffectiveRadius": 1.0,
                "DiffusionCoefficient": 1E-07,
                "molecule_location": 1,
                "entity_guid": "b8126221-1e3c-49da-b2bd-6d30f47b0b1f"
              },
              "Name": "CXCL13:CXCR5|",
              "report_mp": {
                "mp_extended": 2,
                "molpop_guid_ref": "0c7780b0-96c5-4f87-ab75-f6c6d3a20191"
              },
              "mp_distribution": {
                "$type": "Daphne.MolPopHomogeneousLevel, Daphne",
                "concentration": 0.0,
                "mp_distribution_type": 0,
                "boundaryCondition": null
              },
              "renderLabel": "b8126221-1e3c-49da-b2bd-6d30f47b0b1f"
            }
          ],
          "Reactions": [],
          "reaction_complexes": []
        },
        "cytosol": {
          "molpops": [
            {
              "molpop_guid": "0dde43d3-33b7-4444-8022-cd4fa9ab55af",
              "molecule": {
                "Name": "A",
                "renderLabel": "6afbee57-6dcc-4bd6-bc14-1e10116e8388",
                "MolecularWeight": 1.0,
                "EffectiveRadius": 1.0,
                "DiffusionCoefficient": 750.0,
                "molecule_location": 0,
                "entity_guid": "6afbee57-6dcc-4bd6-bc14-1e10116e8388"
              },
              "Name": "A",
              "report_mp": {
                "mp_extended": 2,
                "molpop_guid_ref": "0dde43d3-33b7-4444-8022-cd4fa9ab55af"
              },
              "mp_distribution": {
                "$type": "Daphne.MolPopHomogeneousLevel, Daphne",
                "concentration": 250.0,
                "mp_distribution_type": 0,
                "boundaryCondition": null
              },
              "renderLabel": "6afbee57-6dcc-4bd6-bc14-1e10116e8388"
            },
            {
              "molpop_guid": "cf2fa1fc-41cc-4919-b24b-08eb63283b46",
              "molecule": {
                "Name": "A*",
                "renderLabel": "c7b04294-a127-4801-a4e7-4cfbf86fcfed",
                "MolecularWeight": 1.0,
                "EffectiveRadius": 1.0,
                "DiffusionCoefficient": 7.5,
                "molecule_location": 0,
                "entity_guid": "c7b04294-a127-4801-a4e7-4cfbf86fcfed"
              },
              "Name": "A*",
              "report_mp": {
                "mp_extended": 2,
                "molpop_guid_ref": "cf2fa1fc-41cc-4919-b24b-08eb63283b46"
              },
              "mp_distribution": {
                "$type": "Daphne.MolPopHomogeneousLevel, Daphne",
                "concentration": 0.0,
                "mp_distribution_type": 0,
                "boundaryCondition": null
              },
              "renderLabel": "c7b04294-a127-4801-a4e7-4cfbf86fcfed"
            },
            {
              "molpop_guid": "f7953823-49b3-420f-a43b-c42de20639b6",
              "molecule": {
                "Name": "sApop",
                "renderLabel": "e411f784-cf2a-40b9-9674-61ea12746bd5",
                "MolecularWeight": 1.0,
                "EffectiveRadius": 1.0,
                "DiffusionCoefficient": 1.0,
                "molecule_location": 0,
                "entity_guid": "e411f784-cf2a-40b9-9674-61ea12746bd5"
              },
              "Name": "sApop",
              "report_mp": {
                "mp_extended": 2,
                "molpop_guid_ref": "f7953823-49b3-420f-a43b-c42de20639b6"
              },
              "mp_distribution": {
                "$type": "Daphne.MolPopHomogeneousLevel, Daphne",
                "concentration": 0.0,
                "mp_distribution_type": 0,
                "boundaryCondition": null
              },
              "renderLabel": "e411f784-cf2a-40b9-9674-61ea12746bd5"
            }
          ],
          "Reactions": [
            {
              "reactants_molecule_guid_ref": [
                "6afbee57-6dcc-4bd6-bc14-1e10116e8388"
              ],
              "products_molecule_guid_ref": [
                "c7b04294-a127-4801-a4e7-4cfbf86fcfed"
              ],
              "modifiers_molecule_guid_ref": [
                "b8126221-1e3c-49da-b2bd-6d30f47b0b1f"
              ],
              "reaction_template_guid_ref": "ee8712d9-26be-4a8a-b137-7da1a455eb3e",
              "rate_const": 0.005,
              "TotalReactionString": "A + CXCL13:CXCR5| -> A* + CXCL13:CXCR5|",
              "entity_guid": "7c613bb0-77f6-4e2d-afb0-b0139ddb2601"
            },
            {
              "reactants_molecule_guid_ref": [
                "c7b04294-a127-4801-a4e7-4cfbf86fcfed"
              ],
              "products_molecule_guid_ref": [
                "6afbee57-6dcc-4bd6-bc14-1e10116e8388"
              ],
              "modifiers_molecule_guid_ref": [],
              "reaction_template_guid_ref": "5725c441-7119-4967-a274-9d70d6b72283",
              "rate_const": 0.0005,
              "TotalReactionString": "A* -> A",
              "entity_guid": "19f358cf-0984-4653-a3e1-a296cd186863"
            },
            {
              "reactants_molecule_guid_ref": [],
              "products_molecule_guid_ref": [
                "e411f784-cf2a-40b9-9674-61ea12746bd5"
              ],
              "modifiers_molecule_guid_ref": [
                "9577901c-7701-47fa-8ffe-5bb1a95cfd0c"
              ],
              "reaction_template_guid_ref": "91a501cf-b1ff-42f2-a3b9-0f179f805ce0",
              "rate_const": 1.6666666666666667,
              "TotalReactionString": "gApop -> sApop + gApop",
              "entity_guid": "e50ff360-0592-488c-b941-69797e30dbe6"
            }
          ],
          "reaction_complexes": []
        },
        "genes": [
          {
            "Name": "gApop",
            "CopyNumber": 2,
            "ActivationLevel": 1.0,
            "entity_guid": "9577901c-7701-47fa-8ffe-5bb1a95cfd0c"
          }
        ],
        "diff_scheme": null,
        "death_driver": null,
        "div_scheme": null,
        "entity_guid": "094518dc-b53c-4887-b4e3-7c5ca066e67d"
      }
    ],
    "molecules": [
      {
        "Name": "CXCL13",
        "renderLabel": "8312e805-3bb5-4c0b-afd4-ab5c2333591d",
        "MolecularWeight": 7.96,
        "EffectiveRadius": 1.0,
        "DiffusionCoefficient": 4500.0,
        "molecule_location": 0,
        "entity_guid": "8312e805-3bb5-4c0b-afd4-ab5c2333591d"
      },
      {
        "Name": "A",
        "renderLabel": "6afbee57-6dcc-4bd6-bc14-1e10116e8388",
        "MolecularWeight": 1.0,
        "EffectiveRadius": 1.0,
        "DiffusionCoefficient": 750.0,
        "molecule_location": 0,
        "entity_guid": "6afbee57-6dcc-4bd6-bc14-1e10116e8388"
      },
      {
        "Name": "A*",
        "renderLabel": "c7b04294-a127-4801-a4e7-4cfbf86fcfed",
        "MolecularWeight": 1.0,
        "EffectiveRadius": 1.0,
        "DiffusionCoefficient": 7.5,
        "molecule_location": 0,
        "entity_guid": "c7b04294-a127-4801-a4e7-4cfbf86fcfed"
      },
      {
        "Name": "sApop",
        "renderLabel": "e411f784-cf2a-40b9-9674-61ea12746bd5",
        "MolecularWeight": 1.0,
        "EffectiveRadius": 1.0,
        "DiffusionCoefficient": 1.0,
        "molecule_location": 0,
        "entity_guid": "e411f784-cf2a-40b9-9674-61ea12746bd5"
      },
      {
        "Name": "CXCR5|",
        "renderLabel": "8dbfbfca-2b31-4ba0-a67d-1cb1b2bed436",
        "MolecularWeight": 43.0,
        "EffectiveRadius": 1.0,
        "DiffusionCoefficient": 1E-07,
        "molecule_location": 1,
        "entity_guid": "8dbfbfca-2b31-4ba0-a67d-1cb1b2bed436"
      },
      {
        "Name": "CXCL13:CXCR5|",
        "renderLabel": "b8126221-1e3c-49da-b2bd-6d30f47b0b1f",
        "MolecularWeight": 50.96,
        "EffectiveRadius": 1.0,
        "DiffusionCoefficient": 1E-07,
        "molecule_location": 1,
        "entity_guid": "b8126221-1e3c-49da-b2bd-6d30f47b0b1f"
      }
    ],
    "genes": [
      {
        "Name": "gApop",
        "CopyNumber": 2,
        "ActivationLevel": 1.0,
        "entity_guid": "9577901c-7701-47fa-8ffe-5bb1a95cfd0c"
      }
    ],
    "reactions": [
      {
        "reactants_molecule_guid_ref": [
          "8312e805-3bb5-4c0b-afd4-ab5c2333591d",
          "8dbfbfca-2b31-4ba0-a67d-1cb1b2bed436"
        ],
        "products_molecule_guid_ref": [
          "b8126221-1e3c-49da-b2bd-6d30f47b0b1f"
        ],
        "modifiers_molecule_guid_ref": [],
        "reaction_template_guid_ref": "6175f910-6b3e-4cbe-85c6-ac6842e80dd5",
        "rate_const": 16.25,
        "TotalReactionString": "CXCL13 + CXCR5| -> CXCL13:CXCR5|",
        "entity_guid": "addf048e-319a-4780-a631-f9221eee526f"
      },
      {
        "reactants_molecule_guid_ref": [
          "b8126221-1e3c-49da-b2bd-6d30f47b0b1f"
        ],
        "products_molecule_guid_ref": [
          "8312e805-3bb5-4c0b-afd4-ab5c2333591d",
          "8dbfbfca-2b31-4ba0-a67d-1cb1b2bed436"
        ],
        "modifiers_molecule_guid_ref": [],
        "reaction_template_guid_ref": "0af1638c-bc13-4c3a-9eb1-13772b3c907e",
        "rate_const": 0.494,
        "TotalReactionString": "CXCL13:CXCR5| -> CXCL13 + CXCR5|",
        "entity_guid": "b2b31aad-11ac-41ac-b321-7eb664808900"
      },
      {
        "reactants_molecule_guid_ref": [
          "6afbee57-6dcc-4bd6-bc14-1e10116e8388"
        ],
        "products_molecule_guid_ref": [
          "c7b04294-a127-4801-a4e7-4cfbf86fcfed"
        ],
        "modifiers_molecule_guid_ref": [
          "b8126221-1e3c-49da-b2bd-6d30f47b0b1f"
        ],
        "reaction_template_guid_ref": "ee8712d9-26be-4a8a-b137-7da1a455eb3e",
        "rate_const": 0.005,
        "TotalReactionString": "A + CXCL13:CXCR5| -> A* + CXCL13:CXCR5|",
        "entity_guid": "7c613bb0-77f6-4e2d-afb0-b0139ddb2601"
      },
      {
        "reactants_molecule_guid_ref": [
          "c7b04294-a127-4801-a4e7-4cfbf86fcfed"
        ],
        "products_molecule_guid_ref": [
          "6afbee57-6dcc-4bd6-bc14-1e10116e8388"
        ],
        "modifiers_molecule_guid_ref": [],
        "reaction_template_guid_ref": "5725c441-7119-4967-a274-9d70d6b72283",
        "rate_const": 0.0005,
        "TotalReactionString": "A* -> A",
        "entity_guid": "19f358cf-0984-4653-a3e1-a296cd186863"
      },
      {
        "reactants_molecule_guid_ref": [],
        "products_molecule_guid_ref": [
          "e411f784-cf2a-40b9-9674-61ea12746bd5"
        ],
        "modifiers_molecule_guid_ref": [
          "9577901c-7701-47fa-8ffe-5bb1a95cfd0c"
        ],
        "reaction_template_guid_ref": "91a501cf-b1ff-42f2-a3b9-0f179f805ce0",
        "rate_const": 1.6666666666666667,
        "TotalReactionString": "gApop -> sApop + gApop",
        "entity_guid": "e50ff360-0592-488c-b941-69797e30dbe6"
      },
      {
        "reactants_molecule_guid_ref": [
          "e411f784-cf2a-40b9-9674-61ea12746bd5"
        ],
        "products_molecule_guid_ref": [],
        "modifiers_molecule_guid_ref": [],
        "reaction_template_guid_ref": "4b3fefdd-910f-4d55-9072-17bf517eae97",
        "rate_const": 0.1,
        "TotalReactionString": "sApop ->",
        "entity_guid": "d5a94ba2-fa7c-4683-9c5a-59c194a5dda5"
      }
    ],
    "reaction_templates": [
      {
        "name": "Annihilation",
        "reactants_stoichiometric_const": [
          1
        ],
        "products_stoichiometric_const": [],
        "modifiers_stoichiometric_const": [],
        "isBoundary": false,
        "reac_type": 2,
        "entity_guid": "4b3fefdd-910f-4d55-9072-17bf517eae97"
      },
      {
        "name": "Association",
        "reactants_stoichiometric_const": [
          1,
          1
        ],
        "products_stoichiometric_const": [
          1
        ],
        "modifiers_stoichiometric_const": [],
        "isBoundary": false,
        "reac_type": 0,
        "entity_guid": "3cf7f117-5dc0-47a9-a9dc-67c2ee8ad4af"
      },
      {
        "name": "Dimerization",
        "reactants_stoichiometric_const": [
          2
        ],
        "products_stoichiometric_const": [
          1
        ],
        "modifiers_stoichiometric_const": [],
        "isBoundary": false,
        "reac_type": 3,
        "entity_guid": "9d1c9f89-9170-4443-b802-4748660e2a3e"
      },
      {
        "name": "DimerDissociation",
        "reactants_stoichiometric_const": [
          1
        ],
        "products_stoichiometric_const": [
          2
        ],
        "modifiers_stoichiometric_const": [],
        "isBoundary": false,
        "reac_type": 4,
        "entity_guid": "d94b42cb-8408-4520-9293-a779d2ca04bc"
      },
      {
        "name": "Dissociation",
        "reactants_stoichiometric_const": [
          1
        ],
        "products_stoichiometric_const": [
          1,
          1
        ],
        "modifiers_stoichiometric_const": [],
        "isBoundary": false,
        "reac_type": 1,
        "entity_guid": "935aafe4-ad0c-4f2f-9b53-ff8970ad70a5"
      },
      {
        "name": "Transformation",
        "reactants_stoichiometric_const": [
          1
        ],
        "products_stoichiometric_const": [
          1
        ],
        "modifiers_stoichiometric_const": [],
        "isBoundary": false,
        "reac_type": 5,
        "entity_guid": "5725c441-7119-4967-a274-9d70d6b72283"
      },
      {
        "name": "CatalyzedBoundaryActivation",
        "reactants_stoichiometric_const": [
          1
        ],
        "products_stoichiometric_const": [
          1
        ],
        "modifiers_stoichiometric_const": [
          1
        ],
        "isBoundary": true,
        "reac_type": 14,
        "entity_guid": "ee8712d9-26be-4a8a-b137-7da1a455eb3e"
      },
      {
        "name": "BoundaryAssociation",
        "reactants_stoichiometric_const": [
          1,
          1
        ],
        "products_stoichiometric_const": [
          1
        ],
        "modifiers_stoichiometric_const": [],
        "isBoundary": true,
        "reac_type": 15,
        "entity_guid": "6175f910-6b3e-4cbe-85c6-ac6842e80dd5"
      },
      {
        "name": "BoundaryDissociation",
        "reactants_stoichiometric_const": [
          1
        ],
        "products_stoichiometric_const": [
          1,
          1
        ],
        "modifiers_stoichiometric_const": [],
        "isBoundary": true,
        "reac_type": 16,
        "entity_guid": "0af1638c-bc13-4c3a-9eb1-13772b3c907e"
      },
      {
        "name": "BoundaryTransportTo",
        "reactants_stoichiometric_const": [
          1
        ],
        "products_stoichiometric_const": [
          1
        ],
        "modifiers_stoichiometric_const": [],
        "isBoundary": true,
        "reac_type": 18,
        "entity_guid": "0be00c40-02f3-4e99-8b66-99a667429edf"
      },
      {
        "name": "BoundaryTransportFrom",
        "reactants_stoichiometric_const": [
          1
        ],
        "products_stoichiometric_const": [
          1
        ],
        "modifiers_stoichiometric_const": [],
        "isBoundary": true,
        "reac_type": 19,
        "entity_guid": "36c5a1ee-0967-4753-9fcb-ecf30e76252e"
      },
      {
        "name": "AutocatalyticTransformation",
        "reactants_stoichiometric_const": [
          1,
          1
        ],
        "products_stoichiometric_const": [
          2
        ],
        "modifiers_stoichiometric_const": [],
        "isBoundary": false,
        "reac_type": 6,
        "entity_guid": "21fa54ed-c44e-4b95-a60c-1c826a2d2eb8"
      },
      {
        "name": "CatalyzedAnnihilation",
        "reactants_stoichiometric_const": [
          1
        ],
        "products_stoichiometric_const": [],
        "modifiers_stoichiometric_const": [
          1
        ],
        "isBoundary": false,
        "reac_type": 7,
        "entity_guid": "2552b587-cbf7-4b5f-a622-bab0be8a9bff"
      },
      {
        "name": "CatalyzedAssociation",
        "reactants_stoichiometric_const": [
          1,
          1
        ],
        "products_stoichiometric_const": [
          1
        ],
        "modifiers_stoichiometric_const": [
          1
        ],
        "isBoundary": false,
        "reac_type": 8,
        "entity_guid": "f0a7824a-78cf-4cc9-8f15-3634234efa10"
      },
      {
        "name": "CatalyzedCreation",
        "reactants_stoichiometric_const": [],
        "products_stoichiometric_const": [
          1
        ],
        "modifiers_stoichiometric_const": [
          1
        ],
        "isBoundary": false,
        "reac_type": 9,
        "entity_guid": "6eddb9e8-4547-423d-bd61-45579c56538a"
      },
      {
        "name": "CatalyzedDimerization",
        "reactants_stoichiometric_const": [
          2
        ],
        "products_stoichiometric_const": [
          1
        ],
        "modifiers_stoichiometric_const": [
          1
        ],
        "isBoundary": false,
        "reac_type": 10,
        "entity_guid": "e31a3fb3-b99d-4728-8ef8-44d196f4298a"
      },
      {
        "name": "CatalyzedDimerDissociation",
        "reactants_stoichiometric_const": [
          1
        ],
        "products_stoichiometric_const": [
          2
        ],
        "modifiers_stoichiometric_const": [
          1
        ],
        "isBoundary": false,
        "reac_type": 11,
        "entity_guid": "844bbfb6-f9d3-4ca8-ae9e-10273eff2b51"
      },
      {
        "name": "CatalyzedDissociation",
        "reactants_stoichiometric_const": [
          1
        ],
        "products_stoichiometric_const": [
          1,
          1
        ],
        "modifiers_stoichiometric_const": [
          1
        ],
        "isBoundary": false,
        "reac_type": 13,
        "entity_guid": "872ec754-e1cc-48be-bd7b-bbe682dca804"
      },
      {
        "name": "CatalyzedTransformation",
        "reactants_stoichiometric_const": [
          1
        ],
        "products_stoichiometric_const": [
          1
        ],
        "modifiers_stoichiometric_const": [
          1
        ],
        "isBoundary": false,
        "reac_type": 12,
        "entity_guid": "e0c003dd-0db7-4f88-a519-ecdb9002f1b4"
      },
      {
        "name": "Transcription",
        "reactants_stoichiometric_const": [],
        "products_stoichiometric_const": [
          1
        ],
        "modifiers_stoichiometric_const": [
          1
        ],
        "isBoundary": false,
        "reac_type": 20,
        "entity_guid": "91a501cf-b1ff-42f2-a3b9-0f179f805ce0"
      }
    ],
    "diff_schemes": [],
    "transition_drivers": []
  }
}