{
  "experiment_name": "Blank Vat RC",
  "experiment_reps": 1,
  "experiment_guid": "f48f8aa3-5301-4f13-86fb-faf38bcbcfc3",
  "experiment_description": "...",
  "scenario": {
    "$type": "Daphne.VatReactionComplexScenario, Daphne",
    "popOptions": {
      "cellPopOptions": [],
      "molPopOptions": []
    },
    "time_config": {
      "duration": 2.0,
      "rendering_interval": 0.2,
      "sampling_interval": 0.2,
      "integrator_step": 0.001
    },
    "simInterpolate": 0,
    "simCellSize": 0,
    "environment": {
      "$type": "Daphne.ConfigPointEnvironment, Daphne",
      "comp": {
        "molpops": [],
        "Reactions": [],
        "reaction_complexes": []
      }
    },
    "reactionsReport": false
  },
  "sim_params": {
    "Phagocytosis": {
      "ParamDistr": null,
      "ConstValue": 0.0,
      "DistributionType": 0
    },
    "phi1": 100.0,
    "phi2": 0.0,
    "globalRandomSeed": 1159707502
  },
  "reporter_file_name": "",
  "entity_repository": {
    "reaction_complexes": [],
    "cells": [],
    "molecules": [],
    "genes": [],
    "reactions": [],
    "reaction_templates": [
      {
        "name": "Annihilation",
        "reactants_stoichiometric_const": [
          1
        ],
        "products_stoichiometric_const": [],
        "modifiers_stoichiometric_const": [],
        "isBoundary": false,
        "reac_type": 2,
        "entity_guid": "7f35dc68-421a-4c1e-a040-aa75d7549c2e",
        "description": ""
      },
      {
        "name": "Association",
        "reactants_stoichiometric_const": [
          1,
          1
        ],
        "products_stoichiometric_const": [
          1
        ],
        "modifiers_stoichiometric_const": [],
        "isBoundary": false,
        "reac_type": 0,
        "entity_guid": "7107e6a7-cf30-4d3e-94a0-edc38ffa3855",
        "description": ""
      },
      {
        "name": "Dimerization",
        "reactants_stoichiometric_const": [
          2
        ],
        "products_stoichiometric_const": [
          1
        ],
        "modifiers_stoichiometric_const": [],
        "isBoundary": false,
        "reac_type": 3,
        "entity_guid": "9791d087-838d-4dae-ad08-ed03e04c205c",
        "description": ""
      },
      {
        "name": "DimerDissociation",
        "reactants_stoichiometric_const": [
          1
        ],
        "products_stoichiometric_const": [
          2
        ],
        "modifiers_stoichiometric_const": [],
        "isBoundary": false,
        "reac_type": 4,
        "entity_guid": "d1cf0c4d-2a60-4c1f-b3b4-4641115c7f0e",
        "description": ""
      },
      {
        "name": "Dissociation",
        "reactants_stoichiometric_const": [
          1
        ],
        "products_stoichiometric_const": [
          1,
          1
        ],
        "modifiers_stoichiometric_const": [],
        "isBoundary": false,
        "reac_type": 1,
        "entity_guid": "dceca4a9-1a9d-4ae2-b38e-94de4669656f",
        "description": ""
      },
      {
        "name": "Transformation",
        "reactants_stoichiometric_const": [
          1
        ],
        "products_stoichiometric_const": [
          1
        ],
        "modifiers_stoichiometric_const": [],
        "isBoundary": false,
        "reac_type": 5,
        "entity_guid": "9c02df50-eb1c-4598-a4a9-551f0955e0f6",
        "description": ""
      },
      {
        "name": "CatalyzedBoundaryActivation",
        "reactants_stoichiometric_const": [
          1
        ],
        "products_stoichiometric_const": [
          1
        ],
        "modifiers_stoichiometric_const": [
          1
        ],
        "isBoundary": true,
        "reac_type": 14,
        "entity_guid": "32a08cfc-d71c-4d7c-9948-2237b757c685",
        "description": ""
      },
      {
        "name": "BoundaryAssociation",
        "reactants_stoichiometric_const": [
          1,
          1
        ],
        "products_stoichiometric_const": [
          1
        ],
        "modifiers_stoichiometric_const": [],
        "isBoundary": true,
        "reac_type": 15,
        "entity_guid": "83d5bc22-5c03-4fd4-a777-13b30bfb481b",
        "description": ""
      },
      {
        "name": "BoundaryDissociation",
        "reactants_stoichiometric_const": [
          1
        ],
        "products_stoichiometric_const": [
          1,
          1
        ],
        "modifiers_stoichiometric_const": [],
        "isBoundary": true,
        "reac_type": 16,
        "entity_guid": "e327abcf-908d-4e9f-b055-601bd3717582",
        "description": ""
      },
      {
        "name": "BoundaryTransportTo",
        "reactants_stoichiometric_const": [
          1
        ],
        "products_stoichiometric_const": [
          1
        ],
        "modifiers_stoichiometric_const": [],
        "isBoundary": true,
        "reac_type": 18,
        "entity_guid": "d1dd117e-2bb5-4317-ba5c-4deedd907d98",
        "description": ""
      },
      {
        "name": "BoundaryTransportFrom",
        "reactants_stoichiometric_const": [
          1
        ],
        "products_stoichiometric_const": [
          1
        ],
        "modifiers_stoichiometric_const": [],
        "isBoundary": true,
        "reac_type": 19,
        "entity_guid": "268a4e00-105d-45a8-944b-416c6ca6cd99",
        "description": ""
      },
      {
        "name": "AutocatalyticTransformation",
        "reactants_stoichiometric_const": [
          1,
          1
        ],
        "products_stoichiometric_const": [
          2
        ],
        "modifiers_stoichiometric_const": [],
        "isBoundary": false,
        "reac_type": 6,
        "entity_guid": "de304a7a-dedc-44b0-87e0-ab4e389391ba",
        "description": ""
      },
      {
        "name": "CatalyzedAnnihilation",
        "reactants_stoichiometric_const": [
          1
        ],
        "products_stoichiometric_const": [],
        "modifiers_stoichiometric_const": [
          1
        ],
        "isBoundary": false,
        "reac_type": 7,
        "entity_guid": "0d702084-f629-4bdb-9bce-da99510767e3",
        "description": ""
      },
      {
        "name": "CatalyzedAssociation",
        "reactants_stoichiometric_const": [
          1,
          1
        ],
        "products_stoichiometric_const": [
          1
        ],
        "modifiers_stoichiometric_const": [
          1
        ],
        "isBoundary": false,
        "reac_type": 8,
        "entity_guid": "17b6ee65-2e5f-482e-95d3-87405db98f2f",
        "description": ""
      },
      {
        "name": "CatalyzedCreation",
        "reactants_stoichiometric_const": [],
        "products_stoichiometric_const": [
          1
        ],
        "modifiers_stoichiometric_const": [
          1
        ],
        "isBoundary": false,
        "reac_type": 9,
        "entity_guid": "23a1ab74-f693-41d0-a8c0-aa5372973ee3",
        "description": ""
      },
      {
        "name": "CatalyzedDimerization",
        "reactants_stoichiometric_const": [
          2
        ],
        "products_stoichiometric_const": [
          1
        ],
        "modifiers_stoichiometric_const": [
          1
        ],
        "isBoundary": false,
        "reac_type": 10,
        "entity_guid": "b14afe6b-3953-44e7-8345-eb95bac61a9b",
        "description": ""
      },
      {
        "name": "CatalyzedDimerDissociation",
        "reactants_stoichiometric_const": [
          1
        ],
        "products_stoichiometric_const": [
          2
        ],
        "modifiers_stoichiometric_const": [
          1
        ],
        "isBoundary": false,
        "reac_type": 11,
        "entity_guid": "f5d7a886-5fa6-4c59-a749-d800e0c895a0",
        "description": ""
      },
      {
        "name": "CatalyzedDissociation",
        "reactants_stoichiometric_const": [
          1
        ],
        "products_stoichiometric_const": [
          1,
          1
        ],
        "modifiers_stoichiometric_const": [
          1
        ],
        "isBoundary": false,
        "reac_type": 13,
        "entity_guid": "5e99e331-e188-49a2-a08c-859d6b725d8f",
        "description": ""
      },
      {
        "name": "CatalyzedTransformation",
        "reactants_stoichiometric_const": [
          1
        ],
        "products_stoichiometric_const": [
          1
        ],
        "modifiers_stoichiometric_const": [
          1
        ],
        "isBoundary": false,
        "reac_type": 12,
        "entity_guid": "fba40a2d-96a7-4cdb-b197-4f1a2772d757",
        "description": ""
      },
      {
        "name": "Transcription",
        "reactants_stoichiometric_const": [],
        "products_stoichiometric_const": [
          1
        ],
        "modifiers_stoichiometric_const": [
          1
        ],
        "isBoundary": false,
        "reac_type": 20,
        "entity_guid": "0e60da89-bcd3-4742-8f84-a92b695715bb",
        "description": ""
      }
    ],
    "diff_schemes": [],
    "transition_drivers": []
  }
}